{
  "Australia Cossack": {
    "Unique": "Australia Cossack",
    "Exploration": "0",
    "Drilling": "1.040431648",
    "Production": "2.275102449",
    "Processing": "8.203935789",
    "Upgrading": "0",
    "Maintenance": "0",
    "Waste": "0",
    "Venting, Flaring, and Fugitive Emissions": "36.78736848",
    "Diluent": "0",
    "Miscellaneous": "2.735095456",
    "Transport to Refinery": "8.690421312",
    "Offsite emissions": "-11.05185081",
    "Net lifecycle emissions": "48.68050432",
    "API Gravity": "47.3",
    "Gas-to-Oil-Ratio": "2845.82",
    "Water-to-Oil-Ratio": "0.27",
    "Steam-to-Oil-Ratio": "0",
    "Flaring-to-Oil-Ratio": "20"
  },
  "Canada Hibernia": {
    "Unique": "Canada Hibernia",
    "Exploration": "0",
    "Drilling": "1.117890021",
    "Production": "0.741342953",
    "Processing": "0.81581985",
    "Upgrading": "0",
    "Maintenance": "0",
    "Waste": "0",
    "Venting, Flaring, and Fugitive Emissions": "23.91518132",
    "Diluent": "0",
    "Miscellaneous": "2.856991748",
    "Transport to Refinery": "1.943355214",
    "Offsite emissions": "0.440111037",
    "Net lifecycle emissions": "31.83069214",
    "API Gravity": "34.6",
    "Gas-to-Oil-Ratio": "333",
    "Water-to-Oil-Ratio": "1.83226156",
    "Steam-to-Oil-Ratio": "0",
    "Flaring-to-Oil-Ratio": "20"
  },
  "China Nanhai Light": {
    "Unique": "China Nanhai Light",
    "Exploration": "0",
    "Drilling": "1.167558939",
    "Production": "14.57049562",
    "Processing": "5.570795424",
    "Upgrading": "0",
    "Maintenance": "0",
    "Waste": "0",
    "Venting, Flaring, and Fugitive Emissions": "102.6667809",
    "Diluent": "0",
    "Miscellaneous": "2.741329448",
    "Transport to Refinery": "7.701234306",
    "Offsite emissions": "3.749984668",
    "Net lifecycle emissions": "138.1681793",
    "API Gravity": "43.6",
    "Gas-to-Oil-Ratio": "4925.18815",
    "Water-to-Oil-Ratio": "5.445",
    "Steam-to-Oil-Ratio": "0",
    "Flaring-to-Oil-Ratio": "468.616573"
  },
  "India Bombay High": {
    "Unique": "India Bombay High",
    "Exploration": "0",
    "Drilling": "7.206356471",
    "Production": "55.27686015",
    "Processing": "9.099124726",
    "Upgrading": "0",
    "Maintenance": "0",
    "Waste": "0",
    "Venting, Flaring, and Fugitive Emissions": "116.4155743",
    "Diluent": "0",
    "Miscellaneous": "2.791405463",
    "Transport to Refinery": "5.146902206",
    "Offsite emissions": "1.757042812",
    "Net lifecycle emissions": "197.6932661",
    "API Gravity": "39.4",
    "Gas-to-Oil-Ratio": "15753.50743",
    "Water-to-Oil-Ratio": "8.637671618",
    "Steam-to-Oil-Ratio": "0",
    "Flaring-to-Oil-Ratio": "326.9165333"
  },
  "Iraq Kirkuk": {
    "Unique": "Iraq Kirkuk",
    "Exploration": "0",
    "Drilling": "7.178499222",
    "Production": "5.333612544",
    "Processing": "3.805675122",
    "Upgrading": "0",
    "Maintenance": "0",
    "Waste": "0",
    "Venting, Flaring, and Fugitive Emissions": "127.9407745",
    "Diluent": "0",
    "Miscellaneous": "2.826414359",
    "Transport to Refinery": "6.669340918",
    "Offsite emissions": "-1.730860777",
    "Net lifecycle emissions": "152.0234559",
    "API Gravity": "36",
    "Gas-to-Oil-Ratio": "1297",
    "Water-to-Oil-Ratio": "1.5",
    "Steam-to-Oil-Ratio": "0",
    "Flaring-to-Oil-Ratio": "757.2808156"
  },
  "Kazakhstan Tengiz": {
    "Unique": "Kazakhstan Tengiz",
    "Exploration": "0",
    "Drilling": "1.616189204",
    "Production": "0.233471139",
    "Processing": "1.909890835",
    "Upgrading": "0",
    "Maintenance": "0",
    "Waste": "0",
    "Venting, Flaring, and Fugitive Emissions": "27.62379356",
    "Diluent": "0",
    "Miscellaneous": "2.745076639",
    "Transport to Refinery": "10.37305509",
    "Offsite emissions": "-0.706988403",
    "Net lifecycle emissions": "43.79448806",
    "API Gravity": "46.4",
    "Gas-to-Oil-Ratio": "351",
    "Water-to-Oil-Ratio": "0.09",
    "Steam-to-Oil-Ratio": "0",
    "Flaring-to-Oil-Ratio": "58.08934045"
  },
  "Nigeria Agbami": {
    "Unique": "Nigeria Agbami",
    "Exploration": "0",
    "Drilling": "2.03235598",
    "Production": "15.3618013",
    "Processing": "7.103873217",
    "Upgrading": "0",
    "Maintenance": "0",
    "Waste": "0",
    "Venting, Flaring, and Fugitive Emissions": "39.74719098",
    "Diluent": "0",
    "Miscellaneous": "2.729132766",
    "Transport to Refinery": "4.323689622",
    "Offsite emissions": "1.670236641",
    "Net lifecycle emissions": "72.96828051",
    "API Gravity": "47",
    "Gas-to-Oil-Ratio": "1733",
    "Water-to-Oil-Ratio": "0.45",
    "Steam-to-Oil-Ratio": "0",
    "Flaring-to-Oil-Ratio": "74.93302221"
  },
  "Nigeria Bonny": {
    "Unique": "Nigeria Bonny",
    "Exploration": "0",
    "Drilling": "14.8644049",
    "Production": "0",
    "Processing": "53.54609749",
    "Upgrading": "0",
    "Maintenance": "0",
    "Waste": "0",
    "Venting, Flaring, and Fugitive Emissions": "352.8759036",
    "Diluent": "0",
    "Miscellaneous": "2.843918806",
    "Transport to Refinery": "4.550373956",
    "Offsite emissions": "-114.8153044",
    "Net lifecycle emissions": "313.8653944",
    "API Gravity": "35.3",
    "Gas-to-Oil-Ratio": "20848.68",
    "Water-to-Oil-Ratio": "1.056",
    "Steam-to-Oil-Ratio": "0",
    "Flaring-to-Oil-Ratio": "1523.326565"
  },
  "Nigeria Escravos Beach": {
    "Unique": "Nigeria Escravos Beach",
    "Exploration": "0",
    "Drilling": "1.326324776",
    "Production": "2.64364367",
    "Processing": "3.036338606",
    "Upgrading": "0",
    "Maintenance": "0",
    "Waste": "0",
    "Venting, Flaring, and Fugitive Emissions": "377.3305118",
    "Diluent": "0",
    "Miscellaneous": "2.843918806",
    "Transport to Refinery": "4.55957194",
    "Offsite emissions": "0.041991374",
    "Net lifecycle emissions": "391.782301",
    "API Gravity": "35.8",
    "Gas-to-Oil-Ratio": "2950.6",
    "Water-to-Oil-Ratio": "1.62",
    "Steam-to-Oil-Ratio": "0",
    "Flaring-to-Oil-Ratio": "2546"
  },
  "Nigeria Obagi": {
    "Unique": "Nigeria Obagi",
    "Exploration": "0",
    "Drilling": "13.59842674",
    "Production": "11.02287858",
    "Processing": "49.98599543",
    "Upgrading": "0",
    "Maintenance": "0",
    "Waste": "0",
    "Venting, Flaring, and Fugitive Emissions": "413.2213955",
    "Diluent": "0",
    "Miscellaneous": "2.843918806",
    "Transport to Refinery": "4.682430722",
    "Offsite emissions": "-103.4000743",
    "Net lifecycle emissions": "391.9549715",
    "API Gravity": "35.3",
    "Gas-to-Oil-Ratio": "21408.7",
    "Water-to-Oil-Ratio": "5.85",
    "Steam-to-Oil-Ratio": "0",
    "Flaring-to-Oil-Ratio": "1983.477172"
  },
  "Norway Ekofisk": {
    "Unique": "Norway Ekofisk",
    "Exploration": "0",
    "Drilling": "1.195478718",
    "Production": "20.44751029",
    "Processing": "4.665050326",
    "Upgrading": "0",
    "Maintenance": "0",
    "Waste": "0",
    "Venting, Flaring, and Fugitive Emissions": "29.0452946",
    "Diluent": "0",
    "Miscellaneous": "2.826414359",
    "Transport to Refinery": "3.227503853",
    "Offsite emissions": "-5.604083143",
    "Net lifecycle emissions": "55.80316901",
    "API Gravity": "36",
    "Gas-to-Oil-Ratio": "1145",
    "Water-to-Oil-Ratio": "2.853438416",
    "Steam-to-Oil-Ratio": "0",
    "Flaring-to-Oil-Ratio": "36.99364222"
  },
  "Norway Skarv": {
    "Unique": "Norway Skarv",
    "Exploration": "0",
    "Drilling": "1.495620089",
    "Production": "0",
    "Processing": "16.47194667",
    "Upgrading": "0",
    "Maintenance": "0",
    "Waste": "0",
    "Venting, Flaring, and Fugitive Emissions": "76.79535264",
    "Diluent": "0",
    "Miscellaneous": "2.804478405",
    "Transport to Refinery": "3.189421211",
    "Offsite emissions": "-30.97827038",
    "Net lifecycle emissions": "69.77854863",
    "API Gravity": "38.5",
    "Gas-to-Oil-Ratio": "5463",
    "Water-to-Oil-Ratio": "0.191043025",
    "Steam-to-Oil-Ratio": "0",
    "Flaring-to-Oil-Ratio": "180.1621995"
  },
  "Qatar Bul Hanine": {
    "Unique": "Qatar Bul Hanine",
    "Exploration": "0",
    "Drilling": "1.24896452",
    "Production": "13.92101944",
    "Processing": "5.118693337",
    "Upgrading": "0",
    "Maintenance": "0",
    "Waste": "0",
    "Venting, Flaring, and Fugitive Emissions": "67.72344696",
    "Diluent": "0",
    "Miscellaneous": "2.843918806",
    "Transport to Refinery": "7.654365075",
    "Offsite emissions": "-3.31069128",
    "Net lifecycle emissions": "95.19971687",
    "API Gravity": "35",
    "Gas-to-Oil-Ratio": "1297",
    "Water-to-Oil-Ratio": "10.37185812",
    "Steam-to-Oil-Ratio": "0",
    "Flaring-to-Oil-Ratio": "303.3014924"
  },
  "Russia Samotlor": {
    "Unique": "Russia Samotlor",
    "Exploration": "0",
    "Drilling": "7.512307941",
    "Production": "14.27667608",
    "Processing": "1.191648753",
    "Upgrading": "0",
    "Maintenance": "0",
    "Waste": "0",
    "Venting, Flaring, and Fugitive Emissions": "26.33402333",
    "Diluent": "0",
    "Miscellaneous": "2.843918806",
    "Transport to Refinery": "15.38997627",
    "Offsite emissions": "-0.336163407",
    "Net lifecycle emissions": "67.21238778",
    "API Gravity": "35",
    "Gas-to-Oil-Ratio": "481.78",
    "Water-to-Oil-Ratio": "13.5",
    "Steam-to-Oil-Ratio": "0",
    "Flaring-to-Oil-Ratio": "24.0288744"
  },
  "Saudi Arabia Ghawar": {
    "Unique": "Saudi Arabia Ghawar",
    "Exploration": "0",
    "Drilling": "1.158111367",
    "Production": "1.119589612",
    "Processing": "3.926176234",
    "Upgrading": "0",
    "Maintenance": "0",
    "Waste": "0",
    "Venting, Flaring, and Fugitive Emissions": "26.21403644",
    "Diluent": "0",
    "Miscellaneous": "2.856991748",
    "Transport to Refinery": "8.134576631",
    "Offsite emissions": "-2.569352152",
    "Net lifecycle emissions": "40.84012988",
    "API Gravity": "34",
    "Gas-to-Oil-Ratio": "570",
    "Water-to-Oil-Ratio": "0.6428565",
    "Steam-to-Oil-Ratio": "0",
    "Flaring-to-Oil-Ratio": "28.94017412"
  },
  "Saudi Arabia Safaniya": {
    "Unique": "Saudi Arabia Safaniya",
    "Exploration": "0",
    "Drilling": "2.301522136",
    "Production": "0",
    "Processing": "0.525971502",
    "Upgrading": "0",
    "Maintenance": "0",
    "Waste": "0",
    "Venting, Flaring, and Fugitive Emissions": "23.09458214",
    "Diluent": "0",
    "Miscellaneous": "2.950718095",
    "Transport to Refinery": "8.294142669",
    "Offsite emissions": "-1.017073187",
    "Net lifecycle emissions": "36.14986336",
    "API Gravity": "27",
    "Gas-to-Oil-Ratio": "225",
    "Water-to-Oil-Ratio": "0.645",
    "Steam-to-Oil-Ratio": "0",
    "Flaring-to-Oil-Ratio": "20"
  },
  "Saudi Arabia Zuluf": {
    "Unique": "Saudi Arabia Zuluf",
    "Exploration": "0",
    "Drilling": "1.046247596",
    "Production": "5.683146033",
    "Processing": "5.894873692",
    "Upgrading": "0",
    "Maintenance": "0",
    "Waste": "0",
    "Venting, Flaring, and Fugitive Emissions": "29.61366483",
    "Diluent": "0",
    "Miscellaneous": "2.883137632",
    "Transport to Refinery": "7.774278769",
    "Offsite emissions": "-6.165632379",
    "Net lifecycle emissions": "46.72971617",
    "API Gravity": "32",
    "Gas-to-Oil-Ratio": "1297",
    "Water-to-Oil-Ratio": "9.048095094",
    "Steam-to-Oil-Ratio": "0",
    "Flaring-to-Oil-Ratio": "20.58021029"
  },
  "United Arab Emirates Fateh": {
    "Unique": "United Arab Emirates Fateh",
    "Exploration": "0",
    "Drilling": "1.359626687",
    "Production": "8.201671328",
    "Processing": "5.327004117",
    "Upgrading": "0",
    "Maintenance": "0",
    "Waste": "0",
    "Venting, Flaring, and Fugitive Emissions": "47.34595324",
    "Diluent": "0",
    "Miscellaneous": "2.896210574",
    "Transport to Refinery": "7.603530384",
    "Offsite emissions": "-0.717674642",
    "Net lifecycle emissions": "72.01632169",
    "API Gravity": "31.8",
    "Gas-to-Oil-Ratio": "4270",
    "Water-to-Oil-Ratio": "1.5",
    "Steam-to-Oil-Ratio": "0",
    "Flaring-to-Oil-Ratio": "96.6604574"
  },
  "United Arab Emirates Murban": {
    "Unique": "United Arab Emirates Murban",
    "Exploration": "0",
    "Drilling": "1.282533651",
    "Production": "0",
    "Processing": "5.7283726",
    "Upgrading": "0",
    "Maintenance": "0",
    "Waste": "0",
    "Venting, Flaring, and Fugitive Emissions": "38.24579311",
    "Diluent": "0",
    "Miscellaneous": "2.778332521",
    "Transport to Refinery": "7.599936214",
    "Offsite emissions": "-6.696944634",
    "Net lifecycle emissions": "48.93802346",
    "API Gravity": "40",
    "Gas-to-Oil-Ratio": "1297",
    "Water-to-Oil-Ratio": "0.15",
    "Steam-to-Oil-Ratio": "0",
    "Flaring-to-Oil-Ratio": "82.44755125"
  },
  "U.S. Bakken": {
    "Unique": "U.S. Bakken",
    "Exploration": "0",
    "Drilling": "4.156026133",
    "Production": "2.620594046",
    "Processing": "1.349406611",
    "Upgrading": "0",
    "Maintenance": "0",
    "Waste": "0",
    "Venting, Flaring, and Fugitive Emissions": "169.9048731",
    "Diluent": "0",
    "Miscellaneous": "2.765259579",
    "Transport to Refinery": "5.419730288",
    "Offsite emissions": "-0.414423387",
    "Net lifecycle emissions": "185.8014664",
    "API Gravity": "41.9",
    "Gas-to-Oil-Ratio": "1273",
    "Water-to-Oil-Ratio": "1.155",
    "Steam-to-Oil-Ratio": "0",
    "Flaring-to-Oil-Ratio": "1043.274952"
  },
  "U.S. Texas Eagle Ford Condensate Zone": {
    "Unique": "U.S. Texas Eagle Ford Condensate Zone",
    "Exploration": "0",
    "Drilling": "7.316508735",
    "Production": "1.317498198",
    "Processing": "10.8841744",
    "Upgrading": "0",
    "Maintenance": "0",
    "Waste": "0",
    "Venting, Flaring, and Fugitive Emissions": "506.7742769",
    "Diluent": "0",
    "Miscellaneous": "2.565996393",
    "Transport to Refinery": "2.033919554",
    "Offsite emissions": "-40.34032156",
    "Net lifecycle emissions": "490.5520526",
    "API Gravity": "58",
    "Gas-to-Oil-Ratio": "8571",
    "Water-to-Oil-Ratio": "1.35",
    "Steam-to-Oil-Ratio": "0",
    "Flaring-to-Oil-Ratio": "3381.102296"
  },
  "U.S. California South Coles Levee": {
    "Unique": "U.S. California South Coles Levee",
    "Exploration": "0",
    "Drilling": "1.312362447",
    "Production": "2.251444823",
    "Processing": "35.6068287",
    "Upgrading": "0",
    "Maintenance": "0",
    "Waste": "0",
    "Venting, Flaring, and Fugitive Emissions": "111.4043669",
    "Diluent": "0",
    "Miscellaneous": "2.741329448",
    "Transport to Refinery": "0.294899977",
    "Offsite emissions": "-73.88732012",
    "Net lifecycle emissions": "79.72391213",
    "API Gravity": "43",
    "Gas-to-Oil-Ratio": "12458.47109",
    "Water-to-Oil-Ratio": "1.413913636",
    "Steam-to-Oil-Ratio": "0",
    "Flaring-to-Oil-Ratio": "26"
  },
  "UK Brent": {
    "Unique": "UK Brent",
    "Exploration": "0",
    "Drilling": "0.759859204",
    "Production": "18.13842621",
    "Processing": "92.0942224",
    "Upgrading": "0",
    "Maintenance": "0",
    "Waste": "0",
    "Venting, Flaring, and Fugitive Emissions": "773.4232811",
    "Diluent": "0",
    "Miscellaneous": "2.817551347",
    "Transport to Refinery": "4.159356531",
    "Offsite emissions": "-145.5093513",
    "Net lifecycle emissions": "745.8833455",
    "API Gravity": "37.5",
    "Gas-to-Oil-Ratio": "33846.90005",
    "Water-to-Oil-Ratio": "131.618989",
    "Steam-to-Oil-Ratio": "0",
    "Flaring-to-Oil-Ratio": "3926.941162"
  },
  "Australia Kingfish": {
    "Unique": "Australia Kingfish",
    "Exploration": "0",
    "Drilling": "0.629542936",
    "Production": "0.02394461",
    "Processing": "2.732004633",
    "Upgrading": "0",
    "Maintenance": "0",
    "Waste": "0",
    "Venting, Flaring, and Fugitive Emissions": "70.92974371",
    "Diluent": "0",
    "Miscellaneous": "2.735095456",
    "Transport to Refinery": "6.643309596",
    "Offsite emissions": "0.714812806",
    "Net lifecycle emissions": "84.40845375",
    "API Gravity": "47",
    "Gas-to-Oil-Ratio": "430.4",
    "Water-to-Oil-Ratio": "1.45754717",
    "Steam-to-Oil-Ratio": "0",
    "Flaring-to-Oil-Ratio": "364"
  },
  "Canada Terra Nova": {
    "Unique": "Canada Terra Nova",
    "Exploration": "0",
    "Drilling": "1.395986773",
    "Production": "12.89262867",
    "Processing": "5.691499826",
    "Upgrading": "0",
    "Maintenance": "0",
    "Waste": "0",
    "Venting, Flaring, and Fugitive Emissions": "77.01830197",
    "Diluent": "0",
    "Miscellaneous": "2.843918806",
    "Transport to Refinery": "2.21737108",
    "Offsite emissions": "-3.751587531",
    "Net lifecycle emissions": "98.30811959",
    "API Gravity": "35",
    "Gas-to-Oil-Ratio": "3650.653443",
    "Water-to-Oil-Ratio": "3.400202085",
    "Steam-to-Oil-Ratio": "0",
    "Flaring-to-Oil-Ratio": "313.7637997"
  },
  "Norway Statfjord": {
    "Unique": "Norway Statfjord",
    "Exploration": "0",
    "Drilling": "7.807115986",
    "Production": "1.169717471",
    "Processing": "36.40914981",
    "Upgrading": "0",
    "Maintenance": "0",
    "Waste": "0",
    "Venting, Flaring, and Fugitive Emissions": "131.1308772",
    "Diluent": "0",
    "Miscellaneous": "2.791405463",
    "Transport to Refinery": "3.830264695",
    "Offsite emissions": "-67.92690395",
    "Net lifecycle emissions": "115.2116266",
    "API Gravity": "39",
    "Gas-to-Oil-Ratio": "11708.44791",
    "Water-to-Oil-Ratio": "29.03865512",
    "Steam-to-Oil-Ratio": "0",
    "Flaring-to-Oil-Ratio": "289.3712716"
  },
  "Canada Athabasca DC SCO": {
    "Unique": "Canada Athabasca DC SCO",
    "Exploration": "0",
    "Drilling": "18.47477902",
    "Production": "37.02684344",
    "Processing": "0",
    "Upgrading": "63.807944",
    "Maintenance": "0",
    "Waste": "0",
    "Venting, Flaring, and Fugitive Emissions": "29.15083304",
    "Diluent": "0",
    "Miscellaneous": "3.218602616",
    "Transport to Refinery": "7.344085432",
    "Offsite emissions": "3.706673402",
    "Net lifecycle emissions": "162.7297609",
    "API Gravity": "",
    "Gas-to-Oil-Ratio": "0",
    "Water-to-Oil-Ratio": "2.5",
    "Steam-to-Oil-Ratio": "",
    "Flaring-to-Oil-Ratio": ""
  }
}
