{
  "Australia Cossack": {
    "Unique": "Australia Cossack",
    "Exploration": "0",
    "Drilling": "1.040431648",
    "Production": "2.113874716",
    "Processing": "8.190521489",
    "Upgrading": "0",
    "Maintenance": "0",
    "Waste": "0",
    "Venting, Flaring, and Fugitive Emissions": "24.63732313",
    "Diluent": "0",
    "Miscellaneous": "2.735095456",
    "Transport to Refinery": "8.690421312",
    "Offsite emissions": "-11.11088015",
    "Net lifecycle emissions": "36.2967876",
    "API Gravity": "47.3",
    "Gas-to-Oil-Ratio": "2785.88",
    "Water-to-Oil-Ratio": "0.18",
    "Steam-to-Oil-Ratio": "0",
    "Flaring-to-Oil-Ratio": "15"
  },
  "Canada Hibernia": {
    "Unique": "Canada Hibernia",
    "Exploration": "0",
    "Drilling": "1.117890021",
    "Production": "0.755259874",
    "Processing": "0.83024609",
    "Upgrading": "0",
    "Maintenance": "0",
    "Waste": "0",
    "Venting, Flaring, and Fugitive Emissions": "17.27241391",
    "Diluent": "0",
    "Miscellaneous": "2.856991748",
    "Transport to Refinery": "1.943355214",
    "Offsite emissions": "0.411980809",
    "Net lifecycle emissions": "25.18813767",
    "API Gravity": "34.6",
    "Gas-to-Oil-Ratio": "333",
    "Water-to-Oil-Ratio": "1.221507707",
    "Steam-to-Oil-Ratio": "0",
    "Flaring-to-Oil-Ratio": "15"
  },
  "China Nanhai Light": {
    "Unique": "China Nanhai Light",
    "Exploration": "0",
    "Drilling": "1.167558939",
    "Production": "8.575309954",
    "Processing": "5.144474646",
    "Upgrading": "0",
    "Maintenance": "0",
    "Waste": "0",
    "Venting, Flaring, and Fugitive Emissions": "69.5133677",
    "Diluent": "0",
    "Miscellaneous": "2.741329448",
    "Transport to Refinery": "7.701234306",
    "Offsite emissions": "0.943162047",
    "Net lifecycle emissions": "95.78643704",
    "API Gravity": "43.6",
    "Gas-to-Oil-Ratio": "3715.1821",
    "Water-to-Oil-Ratio": "3.63",
    "Steam-to-Oil-Ratio": "0",
    "Flaring-to-Oil-Ratio": "351.4624298"
  },
  "India Bombay High": {
    "Unique": "India Bombay High",
    "Exploration": "0",
    "Drilling": "7.206356471",
    "Production": "32.31093935",
    "Processing": "7.66438712",
    "Upgrading": "0",
    "Maintenance": "0",
    "Waste": "0",
    "Venting, Flaring, and Fugitive Emissions": "60.579958",
    "Diluent": "0",
    "Miscellaneous": "2.791405463",
    "Transport to Refinery": "5.146902206",
    "Offsite emissions": "-3.577988086",
    "Net lifecycle emissions": "112.1219605",
    "API Gravity": "39.4",
    "Gas-to-Oil-Ratio": "11434.67162",
    "Water-to-Oil-Ratio": "5.758447745",
    "Steam-to-Oil-Ratio": "0",
    "Flaring-to-Oil-Ratio": "245.1873999"
  },
  "Iraq Kirkuk": {
    "Unique": "Iraq Kirkuk",
    "Exploration": "0",
    "Drilling": "7.178499222",
    "Production": "2.018554277",
    "Processing": "4.349411336",
    "Upgrading": "0",
    "Maintenance": "0",
    "Waste": "0",
    "Venting, Flaring, and Fugitive Emissions": "96.12922099",
    "Diluent": "0",
    "Miscellaneous": "2.826414359",
    "Transport to Refinery": "6.669340918",
    "Offsite emissions": "-3.353692392",
    "Net lifecycle emissions": "115.8177487",
    "API Gravity": "36",
    "Gas-to-Oil-Ratio": "1297",
    "Water-to-Oil-Ratio": "1",
    "Steam-to-Oil-Ratio": "0",
    "Flaring-to-Oil-Ratio": "567.9606117"
  },
  "Kazakhstan Tengiz": {
    "Unique": "Kazakhstan Tengiz",
    "Exploration": "0",
    "Drilling": "1.616189204",
    "Production": "0.247678629",
    "Processing": "2.008117122",
    "Upgrading": "0",
    "Maintenance": "0",
    "Waste": "0",
    "Venting, Flaring, and Fugitive Emissions": "20.31675925",
    "Diluent": "0",
    "Miscellaneous": "2.745076639",
    "Transport to Refinery": "10.37305509",
    "Offsite emissions": "-0.776437405",
    "Net lifecycle emissions": "36.53043853",
    "API Gravity": "46.4",
    "Gas-to-Oil-Ratio": "351",
    "Water-to-Oil-Ratio": "0.06",
    "Steam-to-Oil-Ratio": "0",
    "Flaring-to-Oil-Ratio": "43.56700534"
  },
  "Nigeria Agbami": {
    "Unique": "Nigeria Agbami",
    "Exploration": "0",
    "Drilling": "2.03235598",
    "Production": "9.74946281",
    "Processing": "7.197984391",
    "Upgrading": "0",
    "Maintenance": "0",
    "Waste": "0",
    "Venting, Flaring, and Fugitive Emissions": "28.51202328",
    "Diluent": "0",
    "Miscellaneous": "2.729132766",
    "Transport to Refinery": "4.323689622",
    "Offsite emissions": "0.60971045",
    "Net lifecycle emissions": "55.1543593",
    "API Gravity": "47",
    "Gas-to-Oil-Ratio": "1733",
    "Water-to-Oil-Ratio": "0.3",
    "Steam-to-Oil-Ratio": "0",
    "Flaring-to-Oil-Ratio": "56.19976666"
  },
  "Nigeria Bonny": {
    "Unique": "Nigeria Bonny",
    "Exploration": "0",
    "Drilling": "14.8644049",
    "Production": "0",
    "Processing": "54.64477363",
    "Upgrading": "0",
    "Maintenance": "0",
    "Waste": "0",
    "Venting, Flaring, and Fugitive Emissions": "250.915008",
    "Diluent": "0",
    "Miscellaneous": "2.843918806",
    "Transport to Refinery": "4.550373956",
    "Offsite emissions": "-117.3625816",
    "Net lifecycle emissions": "210.4558977",
    "API Gravity": "35.3",
    "Gas-to-Oil-Ratio": "20848.68",
    "Water-to-Oil-Ratio": "0.704",
    "Steam-to-Oil-Ratio": "0",
    "Flaring-to-Oil-Ratio": "1142.494924"
  },
  "Nigeria Escravos Beach": {
    "Unique": "Nigeria Escravos Beach",
    "Exploration": "0",
    "Drilling": "1.326324776",
    "Production": "2.032195223",
    "Processing": "2.934278775",
    "Upgrading": "0",
    "Maintenance": "0",
    "Waste": "0",
    "Venting, Flaring, and Fugitive Emissions": "281.8830135",
    "Diluent": "0",
    "Miscellaneous": "2.843918806",
    "Transport to Refinery": "4.55957194",
    "Offsite emissions": "0.131614951",
    "Net lifecycle emissions": "295.710918",
    "API Gravity": "35.8",
    "Gas-to-Oil-Ratio": "2220.45",
    "Water-to-Oil-Ratio": "1.08",
    "Steam-to-Oil-Ratio": "0",
    "Flaring-to-Oil-Ratio": "1909.5"
  },
  "Nigeria Obagi": {
    "Unique": "Nigeria Obagi",
    "Exploration": "0",
    "Drilling": "13.59842674",
    "Production": "6.89340451",
    "Processing": "51.03273379",
    "Upgrading": "0",
    "Maintenance": "0",
    "Waste": "0",
    "Venting, Flaring, and Fugitive Emissions": "294.9618164",
    "Diluent": "0",
    "Miscellaneous": "2.843918806",
    "Transport to Refinery": "4.682430722",
    "Offsite emissions": "-107.2777866",
    "Net lifecycle emissions": "266.7349444",
    "API Gravity": "35.3",
    "Gas-to-Oil-Ratio": "20908.72",
    "Water-to-Oil-Ratio": "3.9",
    "Steam-to-Oil-Ratio": "0",
    "Flaring-to-Oil-Ratio": "1487.607879"
  },
  "Norway Ekofisk": {
    "Unique": "Norway Ekofisk",
    "Exploration": "0",
    "Drilling": "1.195478718",
    "Production": "8.178818907",
    "Processing": "4.72156988",
    "Upgrading": "0",
    "Maintenance": "0",
    "Waste": "0",
    "Venting, Flaring, and Fugitive Emissions": "20.29076769",
    "Diluent": "0",
    "Miscellaneous": "2.826414359",
    "Transport to Refinery": "3.227503853",
    "Offsite emissions": "-6.947232799",
    "Net lifecycle emissions": "33.49332061",
    "API Gravity": "36",
    "Gas-to-Oil-Ratio": "1145",
    "Water-to-Oil-Ratio": "1.902292278",
    "Steam-to-Oil-Ratio": "0",
    "Flaring-to-Oil-Ratio": "27.74523167"
  },
  "Norway Skarv": {
    "Unique": "Norway Skarv",
    "Exploration": "0",
    "Drilling": "1.495620089",
    "Production": "0",
    "Processing": "16.60053865",
    "Upgrading": "0",
    "Maintenance": "0",
    "Waste": "0",
    "Venting, Flaring, and Fugitive Emissions": "53.7274893",
    "Diluent": "0",
    "Miscellaneous": "2.804478405",
    "Transport to Refinery": "3.189421211",
    "Offsite emissions": "-31.28064634",
    "Net lifecycle emissions": "46.53690132",
    "API Gravity": "38.5",
    "Gas-to-Oil-Ratio": "5463",
    "Water-to-Oil-Ratio": "0.127362017",
    "Steam-to-Oil-Ratio": "0",
    "Flaring-to-Oil-Ratio": "135.1216496"
  },
  "Qatar Bul Hanine": {
    "Unique": "Qatar Bul Hanine",
    "Exploration": "0",
    "Drilling": "1.24896452",
    "Production": "9.005721829",
    "Processing": "5.337429682",
    "Upgrading": "0",
    "Maintenance": "0",
    "Waste": "0",
    "Venting, Flaring, and Fugitive Emissions": "49.90446679",
    "Diluent": "0",
    "Miscellaneous": "2.843918806",
    "Transport to Refinery": "7.654365075",
    "Offsite emissions": "-4.487952506",
    "Net lifecycle emissions": "71.5069142",
    "API Gravity": "35",
    "Gas-to-Oil-Ratio": "1297",
    "Water-to-Oil-Ratio": "6.91457208",
    "Steam-to-Oil-Ratio": "0",
    "Flaring-to-Oil-Ratio": "227.4761193"
  },
  "Russia Samotlor": {
    "Unique": "Russia Samotlor",
    "Exploration": "0",
    "Drilling": "7.512307941",
    "Production": "9.491506",
    "Processing": "1.208746847",
    "Upgrading": "0",
    "Maintenance": "0",
    "Waste": "0",
    "Venting, Flaring, and Fugitive Emissions": "18.26692151",
    "Diluent": "0",
    "Miscellaneous": "2.843918806",
    "Transport to Refinery": "15.38997627",
    "Offsite emissions": "-1.111211569",
    "Net lifecycle emissions": "53.60216581",
    "API Gravity": "35",
    "Gas-to-Oil-Ratio": "481.78",
    "Water-to-Oil-Ratio": "9",
    "Steam-to-Oil-Ratio": "0",
    "Flaring-to-Oil-Ratio": "18.0216558"
  },
  "Saudi Arabia Ghawar": {
    "Unique": "Saudi Arabia Ghawar",
    "Exploration": "0",
    "Drilling": "1.158111367",
    "Production": "0.86015267",
    "Processing": "3.946259604",
    "Upgrading": "0",
    "Maintenance": "0",
    "Waste": "0",
    "Venting, Flaring, and Fugitive Emissions": "19.11346902",
    "Diluent": "0",
    "Miscellaneous": "2.856991748",
    "Transport to Refinery": "8.134576631",
    "Offsite emissions": "-2.654590037",
    "Net lifecycle emissions": "33.414971",
    "API Gravity": "34",
    "Gas-to-Oil-Ratio": "570",
    "Water-to-Oil-Ratio": "0.428571",
    "Steam-to-Oil-Ratio": "0",
    "Flaring-to-Oil-Ratio": "21.70513059"
  },
  "Saudi Arabia Safaniya": {
    "Unique": "Saudi Arabia Safaniya",
    "Exploration": "0",
    "Drilling": "2.301522136",
    "Production": "0",
    "Processing": "0.540231854",
    "Upgrading": "0",
    "Maintenance": "0",
    "Waste": "0",
    "Venting, Flaring, and Fugitive Emissions": "17.09497352",
    "Diluent": "0",
    "Miscellaneous": "2.950718095",
    "Transport to Refinery": "8.294142669",
    "Offsite emissions": "-1.060754475",
    "Net lifecycle emissions": "30.1208338",
    "API Gravity": "27",
    "Gas-to-Oil-Ratio": "225",
    "Water-to-Oil-Ratio": "0.43",
    "Steam-to-Oil-Ratio": "0",
    "Flaring-to-Oil-Ratio": "15"
  },
  "Saudi Arabia Zuluf": {
    "Unique": "Saudi Arabia Zuluf",
    "Exploration": "0",
    "Drilling": "1.046247596",
    "Production": "4.025868665",
    "Processing": "5.909358369",
    "Upgrading": "0",
    "Maintenance": "0",
    "Waste": "0",
    "Venting, Flaring, and Fugitive Emissions": "21.11741995",
    "Diluent": "0",
    "Miscellaneous": "2.883137632",
    "Transport to Refinery": "7.774278769",
    "Offsite emissions": "-6.516907535",
    "Net lifecycle emissions": "36.23940345",
    "API Gravity": "32",
    "Gas-to-Oil-Ratio": "1297",
    "Water-to-Oil-Ratio": "6.032063396",
    "Steam-to-Oil-Ratio": "0",
    "Flaring-to-Oil-Ratio": "15.43515772"
  },
  "United Arab Emirates Fateh": {
    "Unique": "United Arab Emirates Fateh",
    "Exploration": "0",
    "Drilling": "1.359626687",
    "Production": "6.561337062",
    "Processing": "5.047043826",
    "Upgrading": "0",
    "Maintenance": "0",
    "Waste": "0",
    "Venting, Flaring, and Fugitive Emissions": "28.72974542",
    "Diluent": "0",
    "Miscellaneous": "2.896210574",
    "Transport to Refinery": "7.603530384",
    "Offsite emissions": "-1.12750465",
    "Net lifecycle emissions": "51.0699893",
    "API Gravity": "31.8",
    "Gas-to-Oil-Ratio": "3520",
    "Water-to-Oil-Ratio": "1",
    "Steam-to-Oil-Ratio": "0",
    "Flaring-to-Oil-Ratio": "72.49534305"
  },
  "United Arab Emirates Murban": {
    "Unique": "United Arab Emirates Murban",
    "Exploration": "0",
    "Drilling": "1.282533651",
    "Production": "0",
    "Processing": "5.786769347",
    "Upgrading": "0",
    "Maintenance": "0",
    "Waste": "0",
    "Venting, Flaring, and Fugitive Emissions": "27.41680461",
    "Diluent": "0",
    "Miscellaneous": "2.778332521",
    "Transport to Refinery": "7.599936214",
    "Offsite emissions": "-6.836389952",
    "Net lifecycle emissions": "38.0279864",
    "API Gravity": "40",
    "Gas-to-Oil-Ratio": "1297",
    "Water-to-Oil-Ratio": "0.1",
    "Steam-to-Oil-Ratio": "0",
    "Flaring-to-Oil-Ratio": "61.83566344"
  },
  "U.S. Bakken": {
    "Unique": "U.S. Bakken",
    "Exploration": "0",
    "Drilling": "4.156026133",
    "Production": "2.083052609",
    "Processing": "1.790964218",
    "Upgrading": "0",
    "Maintenance": "0",
    "Waste": "0",
    "Venting, Flaring, and Fugitive Emissions": "126.9272854",
    "Diluent": "0",
    "Miscellaneous": "2.765259579",
    "Transport to Refinery": "5.419730288",
    "Offsite emissions": "-3.56021111",
    "Net lifecycle emissions": "139.5821072",
    "API Gravity": "41.9",
    "Gas-to-Oil-Ratio": "1273",
    "Water-to-Oil-Ratio": "0.77",
    "Steam-to-Oil-Ratio": "0",
    "Flaring-to-Oil-Ratio": "782.4562143"
  },
  "U.S. Texas Eagle Ford Condensate Zone": {
    "Unique": "U.S. Texas Eagle Ford Condensate Zone",
    "Exploration": "0",
    "Drilling": "7.316508735",
    "Production": "0.985541504",
    "Processing": "12.28665056",
    "Upgrading": "0",
    "Maintenance": "0",
    "Waste": "0",
    "Venting, Flaring, and Fugitive Emissions": "374.3515715",
    "Diluent": "0",
    "Miscellaneous": "2.565996393",
    "Transport to Refinery": "2.033919554",
    "Offsite emissions": "-48.27333014",
    "Net lifecycle emissions": "351.2668581",
    "API Gravity": "58",
    "Gas-to-Oil-Ratio": "8571",
    "Water-to-Oil-Ratio": "0.9",
    "Steam-to-Oil-Ratio": "0",
    "Flaring-to-Oil-Ratio": "2535.826722"
  },
  "U.S. California South Coles Levee": {
    "Unique": "U.S. California South Coles Levee",
    "Exploration": "0",
    "Drilling": "1.312362447",
    "Production": "1.762391753",
    "Processing": "35.62561574",
    "Upgrading": "0",
    "Maintenance": "0",
    "Waste": "0",
    "Venting, Flaring, and Fugitive Emissions": "65.50497886",
    "Diluent": "0",
    "Miscellaneous": "2.741329448",
    "Transport to Refinery": "0.294899977",
    "Offsite emissions": "-74.01726466",
    "Net lifecycle emissions": "33.22431357",
    "API Gravity": "43",
    "Gas-to-Oil-Ratio": "12458.47109",
    "Water-to-Oil-Ratio": "0.942609091",
    "Steam-to-Oil-Ratio": "0",
    "Flaring-to-Oil-Ratio": "19.5"
  },
  "UK Brent": {
    "Unique": "UK Brent",
    "Exploration": "0",
    "Drilling": "0.759859204",
    "Production": "18.4956155",
    "Processing": "93.49061236",
    "Upgrading": "0",
    "Maintenance": "0",
    "Waste": "0",
    "Venting, Flaring, and Fugitive Emissions": "546.6931267",
    "Diluent": "0",
    "Miscellaneous": "2.817551347",
    "Transport to Refinery": "4.159356531",
    "Offsite emissions": "-151.289505",
    "Net lifecycle emissions": "515.1266166",
    "API Gravity": "37.5",
    "Gas-to-Oil-Ratio": "33846.90005",
    "Water-to-Oil-Ratio": "87.74599266",
    "Steam-to-Oil-Ratio": "0",
    "Flaring-to-Oil-Ratio": "2945.205872"
  },
  "Australia Kingfish": {
    "Unique": "Australia Kingfish",
    "Exploration": "0",
    "Drilling": "0.629542936",
    "Production": "0.087106168",
    "Processing": "2.8018573",
    "Upgrading": "0",
    "Maintenance": "0",
    "Waste": "0",
    "Venting, Flaring, and Fugitive Emissions": "52.80557793",
    "Diluent": "0",
    "Miscellaneous": "2.735095456",
    "Transport to Refinery": "6.643309596",
    "Offsite emissions": "0.706989999",
    "Net lifecycle emissions": "66.40947939",
    "API Gravity": "47",
    "Gas-to-Oil-Ratio": "363",
    "Water-to-Oil-Ratio": "0.971698113",
    "Steam-to-Oil-Ratio": "0",
    "Flaring-to-Oil-Ratio": "273"
  },
  "Canada Terra Nova": {
    "Unique": "Canada Terra Nova",
    "Exploration": "0",
    "Drilling": "1.395986773",
    "Production": "11.06055602",
    "Processing": "5.757733329",
    "Upgrading": "0",
    "Maintenance": "0",
    "Waste": "0",
    "Venting, Flaring, and Fugitive Emissions": "53.08063747",
    "Diluent": "0",
    "Miscellaneous": "2.843918806",
    "Transport to Refinery": "2.21737108",
    "Offsite emissions": "-4.098410127",
    "Net lifecycle emissions": "72.25779335",
    "API Gravity": "35",
    "Gas-to-Oil-Ratio": "3650.653443",
    "Water-to-Oil-Ratio": "2.26680139",
    "Steam-to-Oil-Ratio": "0",
    "Flaring-to-Oil-Ratio": "235.3228498"
  },
  "Norway Statfjord": {
    "Unique": "Norway Statfjord",
    "Exploration": "0",
    "Drilling": "7.807115986",
    "Production": "1.165518642",
    "Processing": "36.22374881",
    "Upgrading": "0",
    "Maintenance": "0",
    "Waste": "0",
    "Venting, Flaring, and Fugitive Emissions": "89.37557433",
    "Diluent": "0",
    "Miscellaneous": "2.791405463",
    "Transport to Refinery": "3.830264695",
    "Offsite emissions": "-68.49438297",
    "Net lifecycle emissions": "72.69924496",
    "API Gravity": "39",
    "Gas-to-Oil-Ratio": "11708.44791",
    "Water-to-Oil-Ratio": "19.35910341",
    "Steam-to-Oil-Ratio": "0",
    "Flaring-to-Oil-Ratio": "217.0284537"
  },
  "Canada Athabasca DC SCO": {
    "Unique": "Canada Athabasca DC SCO",
    "Exploration": "0",
    "Drilling": "18.47477902",
    "Production": "37.02684344",
    "Processing": "0",
    "Upgrading": "63.807944",
    "Maintenance": "0",
    "Waste": "0",
    "Venting, Flaring, and Fugitive Emissions": "29.15083304",
    "Diluent": "0",
    "Miscellaneous": "3.218602616",
    "Transport to Refinery": "7.344085432",
    "Offsite emissions": "3.706673402",
    "Net lifecycle emissions": "162.7297609",
    "API Gravity": "",
    "Gas-to-Oil-Ratio": "0",
    "Water-to-Oil-Ratio": "2.5",
    "Steam-to-Oil-Ratio": "",
    "Flaring-to-Oil-Ratio": ""
  }
}
